pirg/__init__.py
pirg/config.py
pirg/exceptions.py
pirg/models.py
pirg/pirg.py
pirg/utils.py
test/__init__.py
test/test_commands.py
test/test_utils.py
pirg-1.3.1.dist-info/METADATA
pirg-1.3.1.dist-info/WHEEL
pirg-1.3.1.dist-info/entry_points.txt
pirg-1.3.1.dist-info/top_level.txt
pirg-1.3.1.dist-info/RECORD
