Metadata-Version: 2.1
Name: pirg
Version: 1.3.1
Summary: command-line tool that simplifies the management of project's `requirements.txt` file
Author: kokotin
License: GNU GENERAL PUBLIC LICENSE
Project-URL: Homepage, https://github.com/kokoteen/pirg
Project-URL: Bug Tracker, https://github.com/kokoteen/pirg/issues
Requires-Python: >=3.8
Requires-Dist: typer[all] ==0.9.0
Requires-Dist: requests ==2.31.0
Requires-Dist: packaging ==23.2
Requires-Dist: beautifulsoup4 ==4.12.2
Requires-Dist: fuzzywuzzy[speedup] ==0.9.0
